memoryfn/__init__.py
memoryfn/core/config.py
memoryfn/core/pipeline.py
memoryfn/core/types.py
memoryfn/extraction/facts.py
memoryfn/providers/openai.py
memoryfn/storage/postgres.py
memoryfn-0.0.1.dist-info/METADATA
memoryfn-0.0.1.dist-info/WHEEL
memoryfn-0.0.1.dist-info/RECORD
