Metadata-Version: 2.4
Name: memoryfn
Version: 0.0.1
Summary: Self-hostable AI memory system for agents and applications
Author: 21n
License-Expression: MIT
Requires-Python: >=3.10
Requires-Dist: httpx>=0.27
Requires-Dist: openai>=1.0.0
Requires-Dist: pgvector>=0.2.0
Requires-Dist: psycopg[binary]>=3.1
Requires-Dist: pydantic>=2.6
Requires-Dist: tenacity>=8.0.0
Provides-Extra: dev
Requires-Dist: pytest-asyncio>=0.23.0; extra == 'dev'
Requires-Dist: pytest>=8.0.0; extra == 'dev'
Requires-Dist: ruff>=0.3.0; extra == 'dev'
